logger/__init__.py
logger/es_logger.py
logger/es_total_logger.py
logger/logger.py
logger/logger_factory.py
logger/total_logger.py
tests/__init__.py
tests/logger_test.py
tests/total_logger_test.py
CoEsLogger-0.0.4.dist-info/LICENSE.txt
CoEsLogger-0.0.4.dist-info/METADATA
CoEsLogger-0.0.4.dist-info/WHEEL
CoEsLogger-0.0.4.dist-info/top_level.txt
CoEsLogger-0.0.4.dist-info/RECORD
